django_cloud_provider_zones/LICENSE
django_cloud_provider_zones/__init__.py
django_cloud_provider_zones/admin.py
django_cloud_provider_zones/apps.py
django_cloud_provider_zones/cloud_short_names.py
django_cloud_provider_zones/fixtures/django_cloud_provider_zones-CloudAvailabilityZone.json
django_cloud_provider_zones/fixtures/django_cloud_provider_zones-CloudProvider.json
django_cloud_provider_zones/fixtures/django_cloud_provider_zones-CloudRegion.json
django_cloud_provider_zones/migrations/0001_initial.py
django_cloud_provider_zones/migrations/__init__.py
django_cloud_provider_zones/models.py
django_cloud_provider_zones/serializers.py
django_cloud_provider_zones/tests.py
django_cloud_provider_zones/urls.py
django_cloud_provider_zones/views.py
django_cloud_provider_zones-0.1.13.dist-info/METADATA
django_cloud_provider_zones-0.1.13.dist-info/WHEEL
django_cloud_provider_zones-0.1.13.dist-info/RECORD
