Metadata-Version: 2.1
Name: django-cloud-provider-zones
Version: 0.1.13
Summary: Django app providing a static list of cloud provider regions and AZs
Home-page: https://github.com/yolabingo/django-cloud-provider-zones
License: src/django_cloud_provider_zones/LICENSE
Keywords: django,cloud,provider,regions,aws,gcp
Author: TJ
Author-email: yolabingo@gmail.com
Requires-Python: >=3.10
Classifier: License :: Other/Proprietary License
Classifier: Programming Language :: Python :: 3
Classifier: Programming Language :: Python :: 3.10
Classifier: Programming Language :: Python :: 3.11
Classifier: Programming Language :: Python :: 3.12
Requires-Dist: django (>=5,<6)
Requires-Dist: djangorestframework (>=3.15.0,<4.0.0)
Project-URL: Repository, https://github.com/yolabingo/django-cloud-provider-zones
